Metadata-Version: 2.1
Name: math-tex-writer-belsabbagh
Version: 0.0.1
Summary: Latex math expression writer
Author-email: Belal Elsabbagh <belsabbagh@gmail.com>
License: Copyright © 2023 Belal Elsabbagh
Project-URL: Homepage, https://github.com/belsabbagh/mathex
Keywords: tex,latex,math,expression,pretty-print
Classifier: License :: OSI Approved :: MIT License
Classifier: Programming Language :: Python
Classifier: Programming Language :: Python :: 3
Requires-Python: >=3.8
License-File: LICENSE
Provides-Extra: dev
Requires-Dist: black ; extra == 'dev'
Requires-Dist: bumpver ; extra == 'dev'
Requires-Dist: isort ; extra == 'dev'
Requires-Dist: pip-tools ; extra == 'dev'
Requires-Dist: pytest ; extra == 'dev'
